{
    "items": [
        {
            "crew_details": "SUBMITTED"
        },
        {
            "crew_details": "INPROCESS"
        }
    ],
    "hasMore": false,
    "limit": 25,
    "offset": 0,
    "count": 2,
    "links": [
        {
            "rel": "self",
            "href": "http://129.158.228.138:8080/ords/timerite/CrewRite/CrewRite_StatusDetailsSearch?page_name=crew-time-entry-management"
        },
        {
            "rel": "describedby",
            "href": "http://129.158.228.138:8080/ords/timerite/metadata-catalog/CrewRite/item"
        },
        {
            "rel": "first",
            "href": "http://129.158.228.138:8080/ords/timerite/CrewRite/CrewRite_StatusDetailsSearch?page_name=crew-time-entry-management"
        }
    ]
}